spokestack/__init__.py
spokestack/activation_timeout.py
spokestack/context.py
spokestack/pipeline.py
spokestack/ring_buffer.py
spokestack/utils.py
spokestack/agc/__init__.py
spokestack/agc/webrtc.py
spokestack/asr/__init__.py
spokestack/asr/google/__init__.py
spokestack/asr/google/speech_recognizer.py
spokestack/asr/keyword/__init__.py
spokestack/asr/keyword/tflite.py
spokestack/asr/spokestack/__init__.py
spokestack/asr/spokestack/cloud_client.py
spokestack/asr/spokestack/speech_recognizer.py
spokestack/extensions/__init__.py
spokestack/extensions/webrtc/__init__.py
spokestack/extensions/webrtc/agc.cp37-win_amd64.pyd
spokestack/extensions/webrtc/nsx.cp37-win_amd64.pyd
spokestack/extensions/webrtc/vad.cp37-win_amd64.pyd
spokestack/io/__init__.py
spokestack/io/pyaudio.py
spokestack/io/sound_device.py
spokestack/models/__init__.py
spokestack/models/tensorflow.py
spokestack/nlu/__init__.py
spokestack/nlu/result.py
spokestack/nlu/tflite.py
spokestack/nlu/parsers/__init__.py
spokestack/nlu/parsers/digits.py
spokestack/nlu/parsers/entity.py
spokestack/nlu/parsers/integer.py
spokestack/nlu/parsers/maps.py
spokestack/nlu/parsers/selset.py
spokestack/nsx/__init__.py
spokestack/nsx/webrtc.py
spokestack/profile/__init__.py
spokestack/profile/keyword.py
spokestack/profile/vad_trigger_asr.py
spokestack/profile/wakeword.py
spokestack/profile/wakeword_asr.py
spokestack/tts/__init__.py
spokestack/tts/manager.py
spokestack/tts/clients/__init__.py
spokestack/tts/clients/spokestack.py
spokestack/tts/lite/__init__.py
spokestack/tts/lite/en.py
spokestack/vad/__init__.py
spokestack/vad/webrtc.py
spokestack/wakeword/__init__.py
spokestack/wakeword/tflite.py
tests/__init__.py
tests/test_activation_timeout.py
tests/test_context.py
tests/test_pipeline.py
tests/test_ring_buffer.py
tests/agc/__init__.py
tests/agc/test_webrtc.py
tests/asr/__init__.py
tests/asr/google/__init__.py
tests/asr/google/test_google_speech_recognizer.py
tests/asr/keyword/__init__.py
tests/asr/keyword/test_tflite.py
spokestack-0.0.22.dist-info/LICENSE.txt
spokestack-0.0.22.dist-info/METADATA
spokestack-0.0.22.dist-info/WHEEL
spokestack-0.0.22.dist-info/top_level.txt
spokestack-0.0.22.dist-info/RECORD
