Metadata-Version: 2.1
Name: spokestack
Version: 0.0.22
Summary: Spokestack Library for Python
Home-page: https://github.com/spokestack/spokestack-python
Author: Spokestack
Author-email: support@spokestack.io
License: UNKNOWN
Platform: UNKNOWN
Classifier: Programming Language :: Python :: 3
Classifier: License :: OSI Approved :: Apache Software License
Classifier: Operating System :: OS Independent
Requires-Python: >=3.6
License-File: LICENSE.txt
Requires-Dist: numpy (==1.19.2)
Requires-Dist: Cython (>=0.29.22)
Requires-Dist: websocket-client
Requires-Dist: tokenizers
Requires-Dist: requests
